arcgispro_cli/__init__.py
arcgispro_cli/cli.py
arcgispro_cli/paths.py
arcgispro_cli/addin/ProExporter.addin
arcgispro_cli/commands/__init__.py
arcgispro_cli/commands/clean.py
arcgispro_cli/commands/dump.py
arcgispro_cli/commands/images.py
arcgispro_cli/commands/inspect.py
arcgispro_cli/commands/install.py
arcgispro_cli/commands/launch.py
arcgispro_cli/commands/notebooks.py
arcgispro_cli/commands/open_project.py
arcgispro_cli/commands/query.py
arcgispro_cli/commands/snapshot.py
arcgispro_cli-0.3.1.dist-info/METADATA
arcgispro_cli-0.3.1.dist-info/WHEEL
arcgispro_cli-0.3.1.dist-info/entry_points.txt
arcgispro_cli-0.3.1.dist-info/RECORD
